[
    {
        "id": "GIYDCMBWGY======",
        "sofifaID": "201066",
        "lastUpdate": "Fri Dec 14 13:30:10 2018",
        "picture": "https://cdn.sofifa.org/players/10/19/201066.png",
        "sofifaFollow": "11",
        "position": "SUB",
        "wage": "&euro;18K",
        "value": "&euro;2.3M",
        "potential": "71",
        "rate": "71",
        "jerseyNumber": "7",
        "country": "Germany",
        "team": "Br&oslash;ndby IF",
        "foot": "Right",
        "birthYear": 1988,
        "age": "29",
        "name": "Dominik Kaiser"
    },
    {
        "id": "GE3DCNRTGY======",
        "sofifaID": "161636",
        "lastUpdate": "Fri Dec 14 13:30:10 2018",
        "picture": "https://cdn.sofifa.org/players/10/19/161636.png",
        "sofifaFollow": "9",
        "position": "LDM",
        "wage": "&euro;10K",
        "value": "&euro;950K",
        "potential": "71",
        "rate": "71",
        "jerseyNumber": "10",
        "country": "Paraguay",
        "team": "Rosario Central",
        "foot": "Right",
        "birthYear": 1984,
        "age": "33",
        "name": "N\u00e9stor Ortigoza (N\u00e9stor Ezequiel Ortigoza) "
    },
    {
        "id": "GIZDQOJWG4======",
        "sofifaID": "228967",
        "lastUpdate": "Fri Dec 14 13:30:10 2018",
        "picture": "https://cdn.sofifa.org/players/10/19/228967.png",
        "sofifaFollow": "1",
        "position": "SUB",
        "wage": "&euro;6K",
        "value": "&euro;1.9M",
        "potential": "71",
        "rate": "71",
        "jerseyNumber": "20",
        "country": "Portugal",
        "team": "Boavista FC",
        "foot": "Right",
        "birthYear": 1990,
        "age": "28",
        "name": "Eduardo Jos\u00e9 Borges Machado"
    },
    {
        "id": "GE4TSMRYGI======",
        "sofifaID": "199282",
        "lastUpdate": "Fri Dec 14 13:30:10 2018",
        "picture": "https://cdn.sofifa.org/players/10/19/199282.png",
        "sofifaFollow": "18",
        "position": "RES",
        "wage": "&euro;15K",
        "value": "&euro;1.9M",
        "potential": "71",
        "rate": "71",
        "jerseyNumber": "6",
        "country": "Albania",
        "team": "SC Freiburg",
        "foot": "Right",
        "birthYear": 1990,
        "age": "28",
        "name": "Amir Abrashi"
    },
    {
        "id": "GE3TKNBWGI======",
        "sofifaID": "175462",
        "lastUpdate": "Fri Dec 14 13:30:10 2018",
        "picture": "https://cdn.sofifa.org/players/10/19/175462.png",
        "sofifaFollow": "5",
        "position": "SUB",
        "wage": "&euro;6K",
        "value": "&euro;725K",
        "potential": "71",
        "rate": "71",
        "jerseyNumber": "4",
        "country": "Venezuela",
        "team": "ESTAC Troyes",
        "foot": "Right",
        "birthYear": 1984,
        "age": "34",
        "name": "Oswaldo Vizcarrondo (Oswaldo Augusto Vizcarrondo Ara\u00fajo) "
    },
    {
        "id": "GIZTGMBWGE======",
        "sofifaID": "233061",
        "lastUpdate": "Fri Dec 14 13:30:10 2018",
        "picture": "https://cdn.sofifa.org/players/10/19/233061.png",
        "sofifaFollow": "2",
        "position": "CAM",
        "wage": "&euro;4K",
        "value": "&euro;3.8M",
        "potential": "81",
        "rate": "71",
        "jerseyNumber": "26",
        "country": "Portugal",
        "team": "Clermont Foot 63",
        "foot": "Right",
        "birthYear": 1996,
        "age": "21",
        "name": "Mathias Pereira Lage"
    },
    {
        "id": "GI2DCNZXGE======",
        "sofifaID": "241771",
        "lastUpdate": "Fri Dec 14 13:30:10 2018",
        "picture": "https://cdn.sofifa.org/players/10/19/241771.png",
        "sofifaFollow": "1",
        "position": "LM",
        "wage": "&euro;21K",
        "value": "&euro;2.3M",
        "potential": "71",
        "rate": "71",
        "jerseyNumber": "99",
        "country": "Nigeria",
        "team": "Trabzonspor",
        "foot": "Right",
        "birthYear": 1989,
        "age": "29",
        "name": "Anthony Nwakaeme"
    },
    {
        "id": "GE4TSNZYHE======",
        "sofifaID": "199789",
        "lastUpdate": "Fri Dec 14 13:30:10 2018",
        "picture": "https://cdn.sofifa.org/players/10/19/199789.png",
        "sofifaFollow": "1",
        "position": "LCB",
        "wage": "&euro;11K",
        "value": "&euro;1.8M",
        "potential": "71",
        "rate": "71",
        "jerseyNumber": "22",
        "country": "Turkey",
        "team": "Akhisar Belediyespor",
        "foot": "Right",
        "birthYear": 1987,
        "age": "30",
        "name": "Mustafa Yumlu"
    },
    {
        "id": "GIYTMNRZGI======",
        "sofifaID": "216692",
        "lastUpdate": "Fri Dec 14 13:30:10 2018",
        "picture": "https://cdn.sofifa.org/players/10/19/216692.png",
        "sofifaFollow": "3",
        "position": "SUB",
        "wage": "&euro;6K",
        "value": "&euro;160K",
        "potential": "71",
        "rate": "71",
        "jerseyNumber": "12",
        "country": "Argentina",
        "team": "San Lorenzo de Almagro",
        "foot": "Right",
        "birthYear": 1980,
        "age": "38",
        "name": "Sebasti\u00e1n Torrico (Sebasti\u00e1n Alberto Torrico) "
    },
    {
        "id": "GIZTMNBQGM======",
        "sofifaID": "236403",
        "lastUpdate": "Fri Dec 14 13:30:10 2018",
        "picture": "https://cdn.sofifa.org/players/10/19/236403.png",
        "sofifaFollow": "187",
        "position": "LCB",
        "wage": "&euro;8K",
        "value": "&euro;3.4M",
        "potential": "83",
        "rate": "71",
        "jerseyNumber": "2",
        "country": "France",
        "team": "Eintracht Frankfurt",
        "foot": "Left",
        "birthYear": 1999,
        "age": "18",
        "name": "Evan N'Dicka"
    },
    {
        "id": "GE4TIOJRGY======",
        "sofifaID": "194916",
        "lastUpdate": "Fri Dec 14 13:30:13 2018",
        "picture": "https://cdn.sofifa.org/players/10/19/194916.png",
        "sofifaFollow": "0",
        "position": "SUB",
        "wage": "&euro;5K",
        "value": "&euro;1.2M",
        "potential": "71",
        "rate": "71",
        "jerseyNumber": "1",
        "country": "Portugal",
        "team": "GD Chaves",
        "foot": "Right",
        "birthYear": 1985,
        "age": "33",
        "name": "Ant\u00f3nio Filipe Norinho de Carvalho"
    },
    {
        "id": "GE4TANJXHE======",
        "sofifaID": "190579",
        "lastUpdate": "Fri Dec 14 13:30:13 2018",
        "picture": "https://cdn.sofifa.org/players/10/19/190579.png",
        "sofifaFollow": "1",
        "position": "SUB",
        "wage": "&euro;14K",
        "value": "&euro;1.8M",
        "potential": "71",
        "rate": "71",
        "jerseyNumber": "3",
        "country": "France",
        "team": "Angers SCO",
        "foot": "Right",
        "birthYear": 1989,
        "age": "29",
        "name": "Yoann Andreu"
    },
    {
        "id": "GE4TIOJSGQ======",
        "sofifaID": "194924",
        "lastUpdate": "Fri Dec 14 13:30:13 2018",
        "picture": "https://cdn.sofifa.org/players/10/19/194924.png",
        "sofifaFollow": "1",
        "position": "RDM",
        "wage": "&euro;7K",
        "value": "&euro;1.8M",
        "potential": "71",
        "rate": "71",
        "jerseyNumber": "6",
        "country": "Spain",
        "team": "AD Alcorc&oacute;n",
        "foot": "Left",
        "birthYear": 1988,
        "age": "29",
        "name": "Daniel Toribio Guti\u00e9rrez"
    },
    {
        "id": "GIZDONRYHE======",
        "sofifaID": "227689",
        "lastUpdate": "Fri Dec 14 13:30:13 2018",
        "picture": "https://cdn.sofifa.org/players/10/19/227689.png",
        "sofifaFollow": "40",
        "position": "LCM",
        "wage": "&euro;5K",
        "value": "&euro;3.3M",
        "potential": "77",
        "rate": "71",
        "jerseyNumber": "10",
        "country": "Sweden",
        "team": "Djurg&aring;rdens IF",
        "foot": "Right",
        "birthYear": 1994,
        "age": "24",
        "name": "Kerim Mrabti"
    },
    {
        "id": "GI2DCNZXGU======",
        "sofifaID": "241775",
        "lastUpdate": "Fri Dec 14 13:30:13 2018",
        "picture": "https://cdn.sofifa.org/players/10/19/241775.png",
        "sofifaFollow": "0",
        "position": "SUB",
        "wage": "&euro;10K",
        "value": "&euro;2.3M",
        "potential": "72",
        "rate": "71",
        "jerseyNumber": "4",
        "country": "Morocco",
        "natioalTeam": "Genoa",
        "team": "Perugia",
        "foot": "Right",
        "birthYear": 1992,
        "age": "26",
        "name": "Jawad El Yamiq"
    },
    {
        "id": "GE4DMOJZGA======",
        "sofifaID": "186990",
        "lastUpdate": "Fri Dec 14 13:30:13 2018",
        "picture": "https://cdn.sofifa.org/players/10/19/186990.png",
        "sofifaFollow": "10",
        "position": "SUB",
        "wage": "&euro;20K",
        "value": "&euro;1.8M",
        "potential": "72",
        "rate": "71",
        "jerseyNumberNational": "1",
        "jerseyNumber": "12",
        "country": "Mexico",
        "natioalTeam": "Club Necaxa",
        "team": "Mexico",
        "foot": "Right",
        "birthYear": 1990,
        "age": "27",
        "name": "Hugo Gonz\u00e1lez (Hugo Alfonso Gonz\u00e1lez Dur\u00e1n) "
    },
    {
        "id": "GE3TONJSGI======",
        "sofifaID": "177522",
        "lastUpdate": "Fri Dec 14 13:30:13 2018",
        "picture": "https://cdn.sofifa.org/players/10/19/177522.png",
        "sofifaFollow": "6",
        "position": "RM",
        "wage": "&euro;7K",
        "value": "&euro;1.4M",
        "potential": "71",
        "rate": "71",
        "jerseyNumber": "10",
        "country": "Spain",
        "team": "CD Tenerife",
        "foot": "Right",
        "birthYear": 1985,
        "age": "33",
        "name": "Jes\u00fas Manuel Santana Abreu (Jes\u00fas Manuel  Santana Abreu) "
    },
    {
        "id": "GIYTIMZYHA======",
        "sofifaID": "214388",
        "lastUpdate": "Fri Dec 14 13:30:13 2018",
        "picture": "https://cdn.sofifa.org/players/10/19/214388.png",
        "sofifaFollow": "1",
        "position": "RW",
        "wage": "&euro;14K",
        "value": "&euro;2.3M",
        "potential": "71",
        "rate": "71",
        "jerseyNumber": "70",
        "country": "Colombia",
        "team": "Al Fayha",
        "foot": "Right",
        "birthYear": 1989,
        "age": "29",
        "name": "Danilo Moreno Asprilla"
    },
    {
        "id": "GIZDIMZXGE======",
        "sofifaID": "224371",
        "lastUpdate": "Fri Dec 14 13:30:13 2018",
        "picture": "https://cdn.sofifa.org/players/10/19/224371.png",
        "sofifaFollow": "53",
        "position": "RM",
        "wage": "&euro;13K",
        "value": "&euro;3.8M",
        "potential": "81",
        "rate": "71",
        "jerseyNumber": "20",
        "country": "England",
        "team": "Hull City",
        "foot": "Left",
        "birthYear": 1996,
        "age": "21",
        "name": "Jarrod Bowen"
    },
    {
        "id": "GE4TENRRGM======",
        "sofifaID": "192613",
        "lastUpdate": "Fri Dec 14 13:30:13 2018",
        "picture": "https://cdn.sofifa.org/players/10/19/192613.png",
        "sofifaFollow": "37",
        "position": "GK",
        "wage": "&euro;22K",
        "value": "&euro;1.4M",
        "potential": "71",
        "rate": "71",
        "jerseyNumberNational": "1",
        "jerseyNumber": "1",
        "country": "Romania",
        "natioalTeam": "Romania",
        "team": "Nottingham Forest",
        "foot": "Right",
        "birthYear": 1987,
        "age": "31",
        "name": "Costel Pantilimon"
    },
    {
        "id": "GIYDKMJVHA======",
        "sofifaID": "205158",
        "lastUpdate": "Fri Dec 14 13:30:16 2018",
        "picture": "https://cdn.sofifa.org/players/10/19/205158.png",
        "sofifaFollow": "37",
        "position": "ST",
        "wage": "&euro;8K",
        "value": "&euro;3.2M",
        "potential": "76",
        "rate": "71",
        "jerseyNumber": "19",
        "country": "Spain",
        "team": "CD Numancia",
        "foot": "Right",
        "birthYear": 1993,
        "age": "25",
        "name": "Guillermo Fern\u00e1ndez Hierro"
    },
    {
        "id": "GIYDAMZQHE======",
        "sofifaID": "200309",
        "lastUpdate": "Fri Dec 14 13:30:16 2018",
        "picture": "https://cdn.sofifa.org/players/10/19/200309.png",
        "sofifaFollow": "51",
        "position": "RB",
        "wage": "&euro;27K",
        "value": "&euro;2.3M",
        "potential": "72",
        "rate": "71",
        "jerseyNumber": "27",
        "country": "Zimbabwe",
        "team": "Nottingham Forest",
        "foot": "Right",
        "birthYear": 1991,
        "age": "26",
        "name": "Tendayi Darikwa"
    },
    {
        "id": "GIZTSNZRG4======",
        "sofifaID": "239717",
        "lastUpdate": "Fri Dec 14 13:30:16 2018",
        "picture": "https://cdn.sofifa.org/players/10/19/239717.png",
        "sofifaFollow": "9",
        "position": "SUB",
        "wage": "&euro;1K",
        "value": "&euro;2.7M",
        "potential": "77",
        "rate": "71",
        "jerseyNumber": "94",
        "country": "Ukraine",
        "team": "Shakhtar Donetsk",
        "foot": "Right",
        "birthYear": 1994,
        "age": "23",
        "name": "Oleg Danchenko"
    },
    {
        "id": "GIZDGMBXGQ======",
        "sofifaID": "223074",
        "lastUpdate": "Fri Dec 14 13:30:16 2018",
        "picture": "https://cdn.sofifa.org/players/10/19/223074.png",
        "sofifaFollow": "400",
        "position": "SUB",
        "wage": "&euro;14K",
        "value": "&euro;3.3M",
        "potential": "78",
        "rate": "71",
        "jerseyNumber": "14",
        "country": "Romania",
        "natioalTeam": "Club Brugge KV",
        "team": "AZ Alkmaar",
        "foot": "Left",
        "birthYear": 1995,
        "age": "22",
        "name": "Dorin Rotariu"
    },
    {
        "id": "GIYDGNRTGM======",
        "sofifaID": "203633",
        "lastUpdate": "Fri Dec 14 13:30:16 2018",
        "picture": "https://cdn.sofifa.org/players/10/19/203633.png",
        "sofifaFollow": "249",
        "position": "SUB",
        "wage": "&euro;9K",
        "value": "&euro;3M",
        "potential": "74",
        "rate": "71",
        "jerseyNumber": "77",
        "country": "Belgium",
        "team": "Sporting de Charleroi",
        "foot": "Right",
        "birthYear": 1993,
        "age": "24",
        "name": "Massimo Bruno"
    },
    {
        "id": "GIZTANZXGI======",
        "sofifaID": "230772",
        "lastUpdate": "Fri Dec 14 13:30:16 2018",
        "picture": "https://cdn.sofifa.org/players/10/19/230772.png",
        "sofifaFollow": "0",
        "position": "SUB",
        "wage": "&euro;6K",
        "value": "&euro;1.9M",
        "potential": "71",
        "rate": "71",
        "jerseyNumber": "10",
        "country": "Brazil",
        "team": "Pohang Steelers",
        "foot": "Right",
        "birthYear": 1986,
        "age": "32",
        "name": "Leonardo Gamalho de Souza"
    },
    {
        "id": "GIZDANZYGI======",
        "sofifaID": "220782",
        "lastUpdate": "Fri Dec 14 13:30:16 2018",
        "picture": "https://cdn.sofifa.org/players/10/19/220782.png",
        "sofifaFollow": "11",
        "position": "RDM",
        "wage": "&euro;8K",
        "value": "&euro;2.8M",
        "potential": "77",
        "rate": "71",
        "jerseyNumber": "26",
        "country": "Madagascar",
        "team": "Sporting de Charleroi",
        "foot": "Right",
        "birthYear": 1995,
        "age": "22",
        "name": "Marco Ilaimaharitra"
    },
    {
        "id": "GE4TENRSGE======",
        "sofifaID": "192621",
        "lastUpdate": "Fri Dec 14 13:30:16 2018",
        "picture": "https://cdn.sofifa.org/players/10/19/192621.png",
        "sofifaFollow": "5",
        "position": "SUB",
        "wage": "&euro;11K",
        "value": "&euro;1.4M",
        "potential": "71",
        "rate": "71",
        "jerseyNumber": "24",
        "country": "Cameroon",
        "team": "Akhisar Belediyespor",
        "foot": "Right",
        "birthYear": 1986,
        "age": "32",
        "name": "Dany Nounkeu"
    },
    {
        "id": "GIZDIMZWHA======",
        "sofifaID": "224368",
        "lastUpdate": "Fri Dec 14 13:30:16 2018",
        "picture": "https://cdn.sofifa.org/players/10/19/224368.png",
        "sofifaFollow": "24",
        "position": "LM",
        "wage": "&euro;11K",
        "value": "&euro;3.2M",
        "potential": "77",
        "rate": "71",
        "jerseyNumber": "25",
        "country": "Mali",
        "team": "Stade de Reims",
        "foot": "Right",
        "birthYear": 1994,
        "age": "23",
        "name": "Moussa Doumbia"
    },
    {
        "id": "GIZTIOBVGM======",
        "sofifaID": "234853",
        "lastUpdate": "Fri Dec 14 13:30:16 2018",
        "picture": "https://cdn.sofifa.org/players/10/19/234853.png",
        "sofifaFollow": "1",
        "position": "LDM",
        "wage": "&euro;8K",
        "value": "&euro;2.4M",
        "potential": "71",
        "rate": "71",
        "jerseyNumber": "15",
        "country": "Brazil",
        "team": "Clube Sport Mar&iacute;timo",
        "foot": "Right",
        "birthYear": 1990,
        "age": "28",
        "name": "Jean Cl\u00e9ber Santos da Silva (Jean Cleber Santos da Silva) "
    },
    {
        "id": "GIYDSNZWHE======",
        "sofifaID": "209769",
        "lastUpdate": "Fri Dec 14 13:30:18 2018",
        "picture": "https://cdn.sofifa.org/players/10/19/209769.png",
        "sofifaFollow": "172",
        "position": "LM",
        "wage": "&euro;9K",
        "value": "&euro;3.2M",
        "potential": "76",
        "rate": "71",
        "jerseyNumber": "7",
        "country": "Turkey",
        "team": "Kayserispor",
        "foot": "Right",
        "birthYear": 1995,
        "age": "23",
        "name": "Bilal Ba\u015fa\u00e7\u0131ko\u011flu"
    },
    {
        "id": "GE4TCMBXHE======",
        "sofifaID": "191079",
        "lastUpdate": "Fri Dec 14 13:30:18 2018",
        "picture": "https://cdn.sofifa.org/players/10/19/191079.png",
        "sofifaFollow": "5",
        "position": "LCB",
        "wage": "&euro;17K",
        "value": "&euro;2.4M",
        "potential": "73",
        "rate": "71",
        "jerseyNumber": "12",
        "country": "England",
        "team": "Birmingham City",
        "foot": "Right",
        "birthYear": 1991,
        "age": "26",
        "name": "Harlee Dean"
    },
    {
        "id": "GE4TOMRTGM======",
        "sofifaID": "197233",
        "lastUpdate": "Fri Dec 14 13:30:18 2018",
        "picture": "https://cdn.sofifa.org/players/10/19/197233.png",
        "sofifaFollow": "10",
        "position": "GK",
        "wage": "&euro;14K",
        "value": "&euro;2.1M",
        "potential": "75",
        "rate": "71",
        "jerseyNumber": "16",
        "country": "Senegal",
        "team": "Stade Rennais FC",
        "foot": "Right",
        "birthYear": 1992,
        "age": "26",
        "name": "Abdoulaye Diallo"
    },
    {
        "id": "GIYTONZRGA======",
        "sofifaID": "217710",
        "lastUpdate": "Fri Dec 14 13:30:18 2018",
        "picture": "https://cdn.sofifa.org/players/10/19/217710.png",
        "sofifaFollow": "8",
        "position": "SUB",
        "wage": "&euro;10K",
        "value": "&euro;2.8M",
        "potential": "72",
        "rate": "71",
        "jerseyNumber": "9",
        "country": "Mexico",
        "team": "Club Necaxa",
        "foot": "Right",
        "birthYear": 1991,
        "age": "26",
        "name": "Mart\u00edn Barrag\u00e1n (Mart\u00edn Barrag\u00e1n Negrete) "
    },
    {
        "id": "GE3DSMZSGE======",
        "sofifaID": "169321",
        "lastUpdate": "Fri Dec 14 13:30:18 2018",
        "picture": "https://cdn.sofifa.org/players/10/19/169321.png",
        "sofifaFollow": "1",
        "position": "SUB",
        "wage": "&euro;10K",
        "value": "&euro;1.5M",
        "potential": "71",
        "rate": "71",
        "jerseyNumber": "29",
        "country": "Mexico",
        "natioalTeam": "Club Atlas",
        "team": "U.N.A.M.",
        "foot": "Right",
        "birthYear": 1987,
        "age": "30",
        "name": "Miguel Fraga (Miguel \u00c1ngel Fraga Licona) "
    },
    {
        "id": "GE4DGOJSGE======",
        "sofifaID": "183921",
        "lastUpdate": "Fri Dec 14 13:30:18 2018",
        "picture": "https://cdn.sofifa.org/players/10/19/183921.png",
        "sofifaFollow": "2",
        "position": "RM",
        "wage": "&euro;6K",
        "value": "&euro;2.1M",
        "potential": "71",
        "rate": "71",
        "jerseyNumber": "22",
        "country": "France",
        "team": "Stade Brestois 29",
        "foot": "Right",
        "birthYear": 1987,
        "age": "31",
        "name": "Julien Faussurier"
    },
    {
        "id": "GIZTSNBXGU======",
        "sofifaID": "239475",
        "lastUpdate": "Fri Dec 14 13:30:18 2018",
        "picture": "https://cdn.sofifa.org/players/10/19/239475.png",
        "sofifaFollow": "82",
        "position": "SUB",
        "wage": "&euro;13K",
        "value": "&euro;3.7M",
        "potential": "81",
        "rate": "71",
        "jerseyNumber": "25",
        "country": "Mexico",
        "team": "Monterrey",
        "foot": "Right",
        "birthYear": 1999,
        "age": "19",
        "name": "Jonathan Gonz\u00e1lez"
    },
    {
        "id": "GIYDAOBSGA======",
        "sofifaID": "200820",
        "lastUpdate": "Fri Dec 14 13:30:18 2018",
        "picture": "https://cdn.sofifa.org/players/10/19/200820.png",
        "sofifaFollow": "157",
        "position": "SUB",
        "wage": "&euro;17K",
        "value": "&euro;2.6M",
        "potential": "75",
        "rate": "71",
        "jerseyNumber": "11",
        "country": "England",
        "team": "Reading",
        "foot": "Left",
        "birthYear": 1993,
        "age": "24",
        "name": "Jordan Obita"
    },
    {
        "id": "GIZTIOBVG4======",
        "sofifaID": "234857",
        "lastUpdate": "Fri Dec 14 13:30:18 2018",
        "picture": "https://cdn.sofifa.org/players/10/19/234857.png",
        "sofifaFollow": "64",
        "position": "SUB",
        "wage": "&euro;1K",
        "value": "&euro;3.9M",
        "potential": "82",
        "rate": "71",
        "jerseyNumber": "98",
        "country": "Russia",
        "team": "PFC CSKA Moscow",
        "foot": "Left",
        "birthYear": 1998,
        "age": "19",
        "name": "Ivan Oblyakov"
    },
    {
        "id": "GIYTCMBWGA======",
        "sofifaID": "211060",
        "lastUpdate": "Fri Dec 14 13:30:18 2018",
        "picture": "https://cdn.sofifa.org/players/10/19/211060.png",
        "sofifaFollow": "16",
        "position": "RB",
        "wage": "&euro;7K",
        "value": "&euro;1.9M",
        "potential": "71",
        "rate": "71",
        "jerseyNumber": "18",
        "country": "Brazil",
        "team": "Kawasaki Frontale",
        "foot": "Right",
        "birthYear": 1989,
        "age": "28",
        "name": "Elson Ferreira de Souza"
    },
    {
        "id": "GEYTEMRUGQ======",
        "sofifaID": "112244",
        "lastUpdate": "Fri Dec 14 13:30:21 2018",
        "picture": "https://cdn.sofifa.org/players/10/19/112244.png",
        "sofifaFollow": "17",
        "position": "SUB",
        "wage": "&euro;18K",
        "value": "&euro;750K",
        "potential": "71",
        "rate": "71",
        "jerseyNumber": "18",
        "country": "Czech Republic",
        "team": "FC Girondins de Bordeaux",
        "foot": "Right",
        "birthYear": 1982,
        "age": "36",
        "name": "Jaroslav Pla\u0161il"
    },
    {
        "id": "GIZDIMJQGM======",
        "sofifaID": "224103",
        "lastUpdate": "Fri Dec 14 13:30:21 2018",
        "picture": "https://cdn.sofifa.org/players/10/19/224103.png",
        "sofifaFollow": "459",
        "position": "SUB",
        "wage": "&euro;14K",
        "value": "&euro;4.1M",
        "potential": "82",
        "rate": "71",
        "jerseyNumberNational": "14",
        "jerseyNumber": "17",
        "country": "Mexico",
        "natioalTeam": "Pachuca",
        "team": "Mexico",
        "foot": "Right",
        "birthYear": 1997,
        "age": "21",
        "name": "Erick Aguirre (Erick Germain Aguirre Tafolla) "
    },
    {
        "id": "GE4TCMBYHE======",
        "sofifaID": "191089",
        "lastUpdate": "Fri Dec 14 13:30:21 2018",
        "picture": "https://cdn.sofifa.org/players/10/19/191089.png",
        "sofifaFollow": "244",
        "position": "SUB",
        "wage": "&euro;32K",
        "value": "&euro;3.1M",
        "potential": "75",
        "rate": "71",
        "jerseyNumber": "21",
        "country": "England",
        "team": "Crystal Palace",
        "foot": "Right",
        "birthYear": 1993,
        "age": "25",
        "name": "Connor Wickham"
    },
    {
        "id": "GIYDIMZYG4======",
        "sofifaID": "204387",
        "lastUpdate": "Fri Dec 14 13:30:21 2018",
        "picture": "https://cdn.sofifa.org/players/10/19/204387.png",
        "sofifaFollow": "1",
        "position": "CAM",
        "wage": "&euro;6K",
        "value": "&euro;2.5M",
        "potential": "71",
        "rate": "71",
        "jerseyNumber": "10",
        "country": "Spain",
        "team": "UD Almer&iacute;a",
        "foot": "Right",
        "birthYear": 1991,
        "age": "27",
        "name": "Juan Carlos Real Ruiz"
    },
    {
        "id": "GE4DGMJUGU======",
        "sofifaID": "183145",
        "lastUpdate": "Fri Dec 14 13:30:21 2018",
        "picture": "https://cdn.sofifa.org/players/10/19/183145.png",
        "sofifaFollow": "5",
        "position": "RB",
        "wage": "&euro;6K",
        "value": "&euro;1.7M",
        "potential": "71",
        "rate": "71",
        "jerseyNumber": "2",
        "country": "England",
        "team": "Aberdeen",
        "foot": "Right",
        "birthYear": 1988,
        "age": "30",
        "name": "Shaleum Logan"
    },
    {
        "id": "GIYDENRQGU======",
        "sofifaID": "202605",
        "lastUpdate": "Fri Dec 14 13:30:21 2018",
        "picture": "https://cdn.sofifa.org/players/10/19/202605.png",
        "sofifaFollow": "44",
        "position": "RCB",
        "wage": "&euro;6K",
        "value": "&euro;2.5M",
        "potential": "74",
        "rate": "71",
        "jerseyNumber": "6",
        "country": "Sweden",
        "team": "AIK",
        "foot": "Right",
        "birthYear": 1992,
        "age": "26",
        "name": "Alexander Milo\u0161evi\u0107 (Alexander Milosevic) "
    },
    {
        "id": "GIZTGMBXGU======",
        "sofifaID": "233075",
        "lastUpdate": "Fri Dec 14 13:30:21 2018",
        "picture": "https://cdn.sofifa.org/players/10/19/233075.png",
        "sofifaFollow": "3",
        "position": "RDM",
        "wage": "&euro;7K",
        "value": "&euro;1.9M",
        "potential": "71",
        "rate": "71",
        "jerseyNumber": "5",
        "country": "Spain",
        "team": "C&aacute;diz CF",
        "foot": "Right",
        "birthYear": 1989,
        "age": "28",
        "name": "Jon Ander Garrido Moracia"
    },
    {
        "id": "GIZDEOBTGI======",
        "sofifaID": "222832",
        "lastUpdate": "Fri Dec 14 13:30:21 2018",
        "picture": "https://cdn.sofifa.org/players/10/19/222832.png",
        "sofifaFollow": "54",
        "position": "SUB",
        "wage": "&euro;7K",
        "value": "&euro;3.1M",
        "potential": "75",
        "rate": "71",
        "jerseyNumber": "24",
        "country": "Portugal",
        "team": "GD Chaves",
        "foot": "Right",
        "birthYear": 1994,
        "age": "24",
        "name": "Jo\u00e3o Rafael Brito Teixeira"
    },
    {
        "id": "GI2DMMZYG4======",
        "sofifaID": "246387",
        "lastUpdate": "Fri Dec 14 13:30:21 2018",
        "picture": "https://cdn.sofifa.org/players/10/19/246387.png",
        "sofifaFollow": "1",
        "position": "RB",
        "wage": "&euro;0",
        "value": "&euro;0",
        "potential": "78",
        "rate": "71",
        "jerseyNumber": "13",
        "country": "Uruguay",
        "team": "Uruguay",
        "foot": "Right",
        "birthYear": 1996,
        "age": "22",
        "name": "Math\u00edas Su\u00e1rez"
    },
    {
        "id": "GE3TQMBTGI======",
        "sofifaID": "178032",
        "lastUpdate": "Fri Dec 14 13:30:21 2018",
        "picture": "https://cdn.sofifa.org/players/10/19/178032.png",
        "sofifaFollow": "6",
        "position": "SUB",
        "wage": "&euro;15K",
        "value": "&euro;1.6M",
        "potential": "71",
        "rate": "71",
        "jerseyNumber": "33",
        "country": "France",
        "natioalTeam": "FC Ingolstadt 04",
        "team": "1. FC Magdeburg",
        "foot": "Right",
        "birthYear": 1986,
        "age": "31",
        "name": "Romain Br\u00e9gerie"
    },
    {
        "id": "GIYTGMBZGI======",
        "sofifaID": "213092",
        "lastUpdate": "Fri Dec 14 13:30:23 2018",
        "picture": "https://cdn.sofifa.org/players/10/19/213092.png",
        "sofifaFollow": "8",
        "position": "CDM",
        "wage": "&euro;5K",
        "value": "&euro;2.7M",
        "potential": "76",
        "rate": "71",
        "jerseyNumberNational": "6",
        "jerseyNumber": "6",
        "country": "Canada",
        "natioalTeam": "Canada",
        "team": "Montreal Impact",
        "foot": "Right",
        "birthYear": 1994,
        "age": "23",
        "name": "Samuel Piette"
    },
    {
        "id": "GE2TSMBYGA======",
        "sofifaID": "159080",
        "lastUpdate": "Fri Dec 14 13:30:23 2018",
        "picture": "https://cdn.sofifa.org/players/10/19/159080.png",
        "sofifaFollow": "10",
        "position": "RCM",
        "wage": "&euro;26K",
        "value": "&euro;2M",
        "potential": "71",
        "rate": "71",
        "jerseyNumber": "4",
        "country": "Scotland",
        "team": "Derby County",
        "foot": "Right",
        "birthYear": 1986,
        "age": "31",
        "name": "Craig Bryson"
    },
    {
        "id": "GIYTIMZXHA======",
        "sofifaID": "214378",
        "lastUpdate": "Fri Dec 14 13:30:23 2018",
        "picture": "https://cdn.sofifa.org/players/10/19/214378.png",
        "sofifaFollow": "2",
        "position": "LCM",
        "wage": "&euro;3K",
        "value": "&euro;2M",
        "potential": "71",
        "rate": "71",
        "jerseyNumber": "14",
        "country": "Colombia",
        "team": "Millonarios FC",
        "foot": "Right",
        "birthYear": 1986,
        "age": "31",
        "name": "David Silva (David Mackalister Silva Mosquera) "
    },
    {
        "id": "GIZDKOJQGA======",
        "sofifaID": "225900",
        "lastUpdate": "Fri Dec 14 13:30:23 2018",
        "picture": "https://cdn.sofifa.org/players/10/19/225900.png",
        "sofifaFollow": "0",
        "position": "SUB",
        "wage": "&euro;0",
        "value": "&euro;0",
        "potential": "74",
        "rate": "71",
        "jerseyNumber": "9",
        "country": "Paraguay",
        "team": "Paraguay",
        "foot": "Right",
        "birthYear": 1992,
        "age": "26",
        "name": "Jos\u00e9 Gabriel Sambenito"
    },
    {
        "id": "GIYDEMZVGY======",
        "sofifaID": "202356",
        "lastUpdate": "Fri Dec 14 13:30:23 2018",
        "picture": "https://cdn.sofifa.org/players/10/19/202356.png",
        "sofifaFollow": "1",
        "position": "LB",
        "wage": "&euro;9K",
        "value": "&euro;1.7M",
        "potential": "71",
        "rate": "71",
        "jerseyNumber": "58",
        "country": "Turkey",
        "team": "Sivasspor",
        "foot": "Left",
        "birthYear": 1988,
        "age": "30",
        "name": "Ziya Erdal"
    },
    {
        "id": "GIYDCNJXGI======",
        "sofifaID": "201572",
        "lastUpdate": "Fri Dec 14 13:30:23 2018",
        "picture": "https://cdn.sofifa.org/players/10/19/201572.png",
        "sofifaFollow": "3",
        "position": "LB",
        "wage": "&euro;0",
        "value": "&euro;0",
        "potential": "71",
        "rate": "71",
        "jerseyNumber": "19",
        "country": "Hungary",
        "team": "Hungary",
        "foot": "Left",
        "birthYear": 1988,
        "age": "29",
        "name": "Mih\u00e1ly Korhut"
    },
    {
        "id": "GIZTSOJXGA======",
        "sofifaID": "239970",
        "lastUpdate": "Fri Dec 14 13:30:23 2018",
        "picture": "https://cdn.sofifa.org/players/10/19/239970.png",
        "sofifaFollow": "1",
        "position": "SUB",
        "wage": "&euro;15K",
        "value": "&euro;4.7M",
        "potential": "86",
        "rate": "71",
        "jerseyNumber": "7",
        "country": "Brazil",
        "team": "Bayer 04 Leverkusen",
        "foot": "Right",
        "birthYear": 2000,
        "age": "17",
        "name": "Paulo Henrique Sampaio Filho"
    },
    {
        "id": "GIYTIMZXGY======",
        "sofifaID": "214376",
        "lastUpdate": "Fri Dec 14 13:30:23 2018",
        "picture": "https://cdn.sofifa.org/players/10/19/214376.png",
        "sofifaFollow": "5",
        "position": "SUB",
        "wage": "&euro;2K",
        "value": "&euro;2M",
        "potential": "71",
        "rate": "71",
        "jerseyNumber": "27",
        "country": "Colombia",
        "team": "Deportivo Cali",
        "foot": "Left",
        "birthYear": 1991,
        "age": "27",
        "name": "Darwin Andrade (Darwin Zamir Andrade Marmolejo) "
    },
    {
        "id": "GIZDIMJQGQ======",
        "sofifaID": "224104",
        "lastUpdate": "Fri Dec 14 13:30:23 2018",
        "picture": "https://cdn.sofifa.org/players/10/19/224104.png",
        "sofifaFollow": "0",
        "position": "RWB",
        "wage": "&euro;13K",
        "value": "&euro;1.9M",
        "potential": "71",
        "rate": "71",
        "jerseyNumber": "4",
        "country": "Argentina",
        "natioalTeam": "Independiente",
        "team": "Uni&oacute;n de Santa Fe",
        "foot": "Right",
        "birthYear": 1990,
        "age": "28",
        "name": "Dami\u00e1n Mart\u00ednez (Dami\u00e1n Alberto Mart\u00ednez) "
    },
    {
        "id": "GIYTANJUHA======",
        "sofifaID": "210548",
        "lastUpdate": "Fri Dec 14 13:30:23 2018",
        "picture": "https://cdn.sofifa.org/players/10/19/210548.png",
        "sofifaFollow": "67",
        "position": "SUB",
        "wage": "&euro;18K",
        "value": "&euro;3.4M",
        "potential": "79",
        "rate": "71",
        "jerseyNumber": "28",
        "country": "Italy",
        "natioalTeam": "Sampdoria",
        "team": "Empoli",
        "foot": "Right",
        "birthYear": 1995,
        "age": "23",
        "name": "Leonardo Capezzi"
    },
    {
        "id": "GIZTENJWGI======",
        "sofifaID": "232562",
        "lastUpdate": "Fri Dec 14 13:30:25 2018",
        "picture": "https://cdn.sofifa.org/players/10/19/232562.png",
        "sofifaFollow": "73",
        "position": "SUB",
        "wage": "&euro;5K",
        "value": "&euro;2.4M",
        "potential": "77",
        "rate": "71",
        "jerseyNumber": "23",
        "country": "Japan",
        "team": "Kashiwa Reysol",
        "foot": "Right",
        "birthYear": 1995,
        "age": "23",
        "name": " \u822a\u8f14"
    },
    {
        "id": "GIZTENZWGA======",
        "sofifaID": "232760",
        "lastUpdate": "Fri Dec 14 13:30:25 2018",
        "picture": "https://cdn.sofifa.org/players/10/19/232760.png",
        "sofifaFollow": "43",
        "position": "LCB",
        "wage": "&euro;2K",
        "value": "&euro;725K",
        "potential": "71",
        "rate": "66",
        "jerseyNumber": "23",
        "country": "Senegal",
        "team": "Korona Kielce",
        "foot": "Left",
        "birthYear": 1994,
        "age": "23",
        "name": "Elhadji Pape Diaw (El Hadji Pape Djibril Diaw) "
    },
    {
        "id": "GIZTGMBRG4======",
        "sofifaID": "233017",
        "lastUpdate": "Fri Dec 14 13:30:25 2018",
        "picture": "https://cdn.sofifa.org/players/10/19/233017.png",
        "sofifaFollow": "1",
        "position": "SUB",
        "wage": "&euro;2K",
        "value": "&euro;1.1M",
        "potential": "78",
        "rate": "66",
        "jerseyNumber": "36",
        "country": "Korea Republic",
        "team": "Daegu FC",
        "foot": "Right",
        "birthYear": 1997,
        "age": "20",
        "name": " \u6734\u9650\u5f6c"
    },
    {
        "id": "GIZTENZWHA======",
        "sofifaID": "232768",
        "lastUpdate": "Fri Dec 14 13:30:25 2018",
        "picture": "https://cdn.sofifa.org/players/10/19/232768.png",
        "sofifaFollow": "0",
        "position": "RB",
        "wage": "&euro;4K",
        "value": "&euro;525K",
        "potential": "66",
        "rate": "66",
        "jerseyNumber": "33",
        "country": "Japan",
        "team": "Sanfrecce Hiroshima",
        "foot": "Left",
        "birthYear": 1990,
        "age": "27",
        "name": " \u62d3\u4e5f"
    },
    {
        "id": "GE4TSNZUGY======",
        "sofifaID": "199746",
        "lastUpdate": "Fri Dec 14 13:30:25 2018",
        "picture": "https://cdn.sofifa.org/players/10/19/199746.png",
        "sofifaFollow": "0",
        "position": "RB",
        "wage": "&euro;3K",
        "value": "&euro;500K",
        "potential": "66",
        "rate": "66",
        "jerseyNumber": "3",
        "country": "Denmark",
        "team": "Hobro IK",
        "foot": "Right",
        "birthYear": 1990,
        "age": "28",
        "name": "Jesper B\u00f8ge (Jesper B\u00f8ge Pedersen) "
    },
    {
        "id": "GIZTKNJXHE======",
        "sofifaID": "235579",
        "lastUpdate": "Fri Dec 14 13:30:25 2018",
        "picture": "https://cdn.sofifa.org/players/10/19/235579.png",
        "sofifaFollow": "1",
        "position": "LB",
        "wage": "&euro;3K",
        "value": "&euro;700K",
        "potential": "70",
        "rate": "66",
        "jerseyNumber": "3",
        "country": "Netherlands",
        "team": "Waasland-Beveren",
        "foot": "Left",
        "birthYear": 1993,
        "age": "24",
        "name": "Milan Massop"
    },
    {
        "id": "GIZDEMRWGM======",
        "sofifaID": "222263",
        "lastUpdate": "Fri Dec 14 13:30:25 2018",
        "picture": "https://cdn.sofifa.org/players/10/19/222263.png",
        "sofifaFollow": "26",
        "position": "SUB",
        "wage": "&euro;2K",
        "value": "&euro;750K",
        "potential": "75",
        "rate": "66",
        "jerseyNumber": "30",
        "country": "Belgium",
        "team": "KRC Genk",
        "foot": "Right",
        "birthYear": 1997,
        "age": "20",
        "name": "Nordin Jackers"
    },
    {
        "id": "GIZDQMJVGY======",
        "sofifaID": "228156",
        "lastUpdate": "Fri Dec 14 13:30:25 2018",
        "picture": "https://cdn.sofifa.org/players/10/19/228156.png",
        "sofifaFollow": "8",
        "position": "LB",
        "wage": "&euro;1K",
        "value": "&euro;900K",
        "potential": "76",
        "rate": "66",
        "jerseyNumber": "18",
        "country": "Colombia",
        "team": "Rionegro &Aacute;guilas",
        "foot": "Left",
        "birthYear": 1997,
        "age": "21",
        "name": "lvaro Angulo"
    },
    {
        "id": "GIYTIOBUGM======",
        "sofifaID": "214843",
        "lastUpdate": "Fri Dec 14 13:30:25 2018",
        "picture": "https://cdn.sofifa.org/players/10/19/214843.png",
        "sofifaFollow": "0",
        "position": "SUB",
        "wage": "&euro;1K",
        "value": "&euro;425K",
        "potential": "66",
        "rate": "66",
        "jerseyNumber": "4",
        "country": "Chile",
        "team": "Curic&oacute; Unido",
        "foot": "Left",
        "birthYear": 1987,
        "age": "31",
        "name": "Eric Godoy (Eric Orlando Godoy Zepeda) "
    },
    {
        "id": "GE4DIMZXGY======",
        "sofifaID": "184376",
        "lastUpdate": "Fri Dec 14 13:30:25 2018",
        "picture": "https://cdn.sofifa.org/players/10/19/184376.png",
        "sofifaFollow": "22",
        "position": "SUB",
        "wage": "&euro;1K",
        "value": "&euro;500K",
        "potential": "66",
        "rate": "66",
        "jerseyNumber": "6",
        "country": "Czech Republic",
        "team": "Sparta Praha",
        "foot": "Right",
        "birthYear": 1989,
        "age": "29",
        "name": "Luk\u00e1\u0161 V\u00e1cha"
    },
    {
        "id": "GIZTQMZZGI======",
        "sofifaID": "238392",
        "lastUpdate": "Fri Dec 14 13:30:31 2018",
        "picture": "https://cdn.sofifa.org/players/10/19/238392.png",
        "sofifaFollow": "1",
        "position": "CDM",
        "wage": "&euro;10K",
        "value": "&euro;1.3M",
        "potential": "80",
        "rate": "66",
        "jerseyNumber": "17",
        "country": "France",
        "natioalTeam": "Olympique Lyonnais",
        "team": "FC Sochaux-Montb&eacute;liard",
        "foot": "Right",
        "birthYear": 1997,
        "age": "20",
        "name": "Elisha Owusu"
    },
    {
        "id": "GIZDQNRXGU======",
        "sofifaID": "228675",
        "lastUpdate": "Fri Dec 14 13:30:31 2018",
        "picture": "https://cdn.sofifa.org/players/10/19/228675.png",
        "sofifaFollow": "7",
        "position": "SUB",
        "wage": "&euro;1K",
        "value": "&euro;925K",
        "potential": "76",
        "rate": "66",
        "jerseyNumber": "36",
        "country": "Russia",
        "team": "Lokomotiv Moscow",
        "foot": "Left",
        "birthYear": 1996,
        "age": "21",
        "name": "Dmitriy Barinov"
    },
    {
        "id": "MNQWYY3VNRQXI33S",
        "sofifaID": "calculator",
        "lastUpdate": "Fri Dec 14 13:30:31 2018",
        "picture": "https://cdn.sofifa.org/players/4/19/240130.png",
        "natioalTeam": "Napoli",
        "team": "FC Porto"
    },
    {
        "id": "GIZTKNJYGI======",
        "sofifaID": "235582",
        "lastUpdate": "Fri Dec 14 13:30:31 2018",
        "picture": "https://cdn.sofifa.org/players/10/19/235582.png",
        "sofifaFollow": "153",
        "position": "RES",
        "wage": "&euro;8K",
        "value": "&euro;725K",
        "potential": "74",
        "rate": "66",
        "jerseyNumber": "40",
        "country": "France",
        "team": "AS Monaco",
        "foot": "Right",
        "birthYear": 1998,
        "age": "20",
        "name": "Lo\u00efc Badiashile (Lo\u00efc Badiashile Mukinayi) "
    },
    {
        "id": "GIYDANJQGU======",
        "sofifaID": "200505",
        "lastUpdate": "Fri Dec 14 13:30:31 2018",
        "picture": "https://cdn.sofifa.org/players/10/19/200505.png",
        "sofifaFollow": "0",
        "position": "SUB",
        "wage": "&euro;3K",
        "value": "&euro;650K",
        "potential": "66",
        "rate": "66",
        "jerseyNumber": "25",
        "country": "Netherlands",
        "team": "Fortuna Sittard",
        "foot": "Right",
        "birthYear": 1990,
        "age": "28",
        "name": "Lars Hutten"
    },
    {
        "id": "GIZDIMBWGI======",
        "sofifaID": "224062",
        "lastUpdate": "Fri Dec 14 13:30:31 2018",
        "picture": "https://cdn.sofifa.org/players/10/19/224062.png",
        "sofifaFollow": "3",
        "position": "RDM",
        "wage": "&euro;2K",
        "value": "&euro;825K",
        "potential": "74",
        "rate": "66",
        "jerseyNumber": "10",
        "country": "Poland",
        "team": "Piast Gliwice",
        "foot": "Right",
        "birthYear": 1998,
        "age": "20",
        "name": "Patryk Dziczek"
    },
    {
        "id": "GIYTIMZTHE======",
        "sofifaID": "214339",
        "lastUpdate": "Fri Dec 14 13:30:31 2018",
        "picture": "https://cdn.sofifa.org/players/10/19/214339.png",
        "sofifaFollow": "8",
        "position": "LCB",
        "wage": "&euro;1K",
        "value": "&euro;750K",
        "potential": "72",
        "rate": "66",
        "jerseyNumber": "3",
        "country": "Colombia",
        "team": "Junior FC",
        "foot": "Right",
        "birthYear": 1993,
        "age": "24",
        "name": "Deivy Balanta (Deivy Alexander Balanta Abon\u00eda) "
    },
    {
        "id": "GI2DAOJVGY======",
        "sofifaID": "240956",
        "lastUpdate": "Fri Dec 14 13:30:31 2018",
        "picture": "https://cdn.sofifa.org/players/10/19/240956.png",
        "sofifaFollow": "1",
        "position": "LB",
        "wage": "&euro;3K",
        "value": "&euro;1.3M",
        "potential": "80",
        "rate": "66",
        "jerseyNumber": "32",
        "country": "Argentina",
        "team": "Gimnasia y Esgrima La Plata",
        "foot": "Left",
        "birthYear": 1998,
        "age": "20",
        "name": "Mat\u00edas Melluso (Mat\u00edas Germ\u00e1n Melluso) "
    },
    {
        "id": "GIZDIOBSGY======",
        "sofifaID": "224826",
        "lastUpdate": "Fri Dec 14 13:30:31 2018",
        "picture": "https://cdn.sofifa.org/players/10/19/224826.png",
        "sofifaFollow": "26",
        "position": "LM",
        "wage": "&euro;5K",
        "value": "&euro;1M",
        "potential": "75",
        "rate": "66",
        "jerseyNumber": "14",
        "country": "France",
        "natioalTeam": "Stade de Reims",
        "team": "Red Star FC",
        "foot": "Left",
        "birthYear": 1995,
        "age": "22",
        "name": "Gr\u00e9gory Berthier"
    },
    {
        "id": "GIZTAMRQGA======",
        "sofifaID": "230200",
        "lastUpdate": "Fri Dec 14 13:30:31 2018",
        "picture": "https://cdn.sofifa.org/players/10/19/230200.png",
        "sofifaFollow": "0",
        "position": "SUB",
        "wage": "&euro;6K",
        "value": "&euro;475K",
        "potential": "66",
        "rate": "66",
        "jerseyNumber": "15",
        "country": "Brazil",
        "team": "Cear&aacute; Sporting Club",
        "foot": "Right",
        "birthYear": 1988,
        "age": "30",
        "name": "Edenildo Eloi Lagoas Regalo"
    },
    {
        "id": "GIZDINJWGY======",
        "sofifaID": "224566",
        "lastUpdate": "Fri Dec 14 13:30:33 2018",
        "picture": "https://cdn.sofifa.org/players/10/19/224566.png",
        "sofifaFollow": "226",
        "position": "RES",
        "wage": "&euro;7K",
        "value": "&euro;825K",
        "potential": "74",
        "rate": "66",
        "jerseyNumber": "31",
        "country": "Spain",
        "team": "Villarreal CF",
        "foot": "Right",
        "birthYear": 1996,
        "age": "22",
        "name": "Carlos Blanco Moreno"
    },
    {
        "id": "GIYTGOBSGI======",
        "sofifaID": "213822",
        "lastUpdate": "Fri Dec 14 13:30:33 2018",
        "picture": "https://cdn.sofifa.org/players/10/19/213822.png",
        "sofifaFollow": "0",
        "position": "SUB",
        "wage": "&euro;1K",
        "value": "&euro;700K",
        "potential": "70",
        "rate": "66",
        "jerseyNumber": "21",
        "country": "Chile",
        "team": "Audax Italiano",
        "foot": "Right",
        "birthYear": 1994,
        "age": "24",
        "name": "Luis Cabrera (Luis Alberto Cabrera Figueroa) "
    },
    {
        "id": "GE4TGMBYG4======",
        "sofifaID": "193087",
        "lastUpdate": "Fri Dec 14 13:30:33 2018",
        "picture": "https://cdn.sofifa.org/players/10/19/193087.png",
        "sofifaFollow": "0",
        "position": "SUB",
        "wage": "&euro;3K",
        "value": "&euro;475K",
        "potential": "66",
        "rate": "66",
        "jerseyNumber": "77",
        "country": "Poland",
        "team": "Lech Pozna\u0144",
        "foot": "Left",
        "birthYear": 1987,
        "age": "30",
        "name": "Piotr Tomasik"
    },
    {
        "id": "GIZDIMBWG4======",
        "sofifaID": "224067",
        "lastUpdate": "Fri Dec 14 13:30:33 2018",
        "picture": "https://cdn.sofifa.org/players/10/19/224067.png",
        "sofifaFollow": "3",
        "position": "CB",
        "wage": "&euro;4K",
        "value": "&euro;725K",
        "potential": "71",
        "rate": "66",
        "jerseyNumber": "6",
        "country": "Denmark",
        "team": "Odense Boldklub",
        "foot": "Right",
        "birthYear": 1993,
        "age": "25",
        "name": "Jeppe Tverskov"
    },
    {
        "id": "GI2DKMBVHA======",
        "sofifaID": "245058",
        "lastUpdate": "Fri Dec 14 13:30:33 2018",
        "picture": "https://cdn.sofifa.org/players/10/19/245058.png",
        "sofifaFollow": "1",
        "position": "RCM",
        "wage": "&euro;5K",
        "value": "&euro;1.1M",
        "potential": "77",
        "rate": "66",
        "jerseyNumber": "9",
        "country": "Georgia",
        "team": "SK Sturm Graz",
        "foot": "Right",
        "birthYear": 1996,
        "age": "22",
        "name": "Otar Kiteishvili"
    },
    {
        "id": "GIZTQNRUHE======",
        "sofifaID": "238649",
        "lastUpdate": "Fri Dec 14 13:30:33 2018",
        "picture": "https://cdn.sofifa.org/players/10/19/238649.png",
        "sofifaFollow": "0",
        "position": "LDM",
        "wage": "&euro;1K",
        "value": "&euro;525K",
        "potential": "66",
        "rate": "66",
        "jerseyNumber": "19",
        "country": "Germany",
        "team": "FSV Zwickau",
        "foot": "Right",
        "birthYear": 1990,
        "age": "28",
        "name": "Davy Frick"
    },
    {
        "id": "GIZTKOBTGQ======",
        "sofifaID": "235834",
        "lastUpdate": "Fri Dec 14 13:30:33 2018",
        "picture": "https://cdn.sofifa.org/players/10/19/235834.png",
        "sofifaFollow": "4",
        "position": "SUB",
        "wage": "&euro;4K",
        "value": "&euro;1.2M",
        "potential": "79",
        "rate": "66",
        "jerseyNumber": "27",
        "country": "Italy",
        "team": "Chievo Verona",
        "foot": "Right",
        "birthYear": 1997,
        "age": "21",
        "name": "Fabio Depaoli"
    },
    {
        "id": "GE3TAOBRHA======",
        "sofifaID": "170818",
        "lastUpdate": "Fri Dec 14 13:30:33 2018",
        "picture": "https://cdn.sofifa.org/players/10/19/170818.png",
        "sofifaFollow": "3",
        "position": "RES",
        "wage": "&euro;4K",
        "value": "&euro;625K",
        "potential": "66",
        "rate": "66",
        "jerseyNumber": "26",
        "country": "England",
        "team": "Blackpool",
        "foot": "Left",
        "birthYear": 1987,
        "age": "30",
        "name": "Steven Davies (Steve Davies) "
    },
    {
        "id": "GE3TONZRHE======",
        "sofifaID": "177719",
        "lastUpdate": "Fri Dec 14 13:30:33 2018",
        "picture": "https://cdn.sofifa.org/players/10/19/177719.png",
        "sofifaFollow": "1",
        "position": "RB",
        "wage": "&euro;2K",
        "value": "&euro;350K",
        "potential": "66",
        "rate": "66",
        "jerseyNumber": "28",
        "country": "Poland",
        "team": "\u015al\u0105sk Wroc\u0142aw",
        "foot": "Right",
        "birthYear": 1985,
        "age": "32",
        "name": "ukasz Bro\u017a"
    },
    {
        "id": "GIZTCMRSG4======",
        "sofifaID": "231227",
        "lastUpdate": "Fri Dec 14 13:30:33 2018",
        "picture": "https://cdn.sofifa.org/players/10/19/231227.png",
        "sofifaFollow": "69",
        "position": "RDM",
        "wage": "&euro;3K",
        "value": "&euro;1.1M",
        "potential": "79",
        "rate": "66",
        "jerseyNumber": "36",
        "country": "Germany",
        "team": "1. FC Heidenheim 1846",
        "foot": "Right",
        "birthYear": 1998,
        "age": "20",
        "name": "Niklas Dorsch"
    },
    {
        "id": "GIYDMMJTGQ======",
        "sofifaID": "206134",
        "lastUpdate": "Fri Dec 14 13:30:36 2018",
        "picture": "https://cdn.sofifa.org/players/10/19/206134.png",
        "sofifaFollow": "248",
        "position": "SUB",
        "wage": "&euro;14K",
        "value": "&euro;925K",
        "potential": "73",
        "rate": "66",
        "jerseyNumber": "44",
        "country": "England",
        "natioalTeam": "Wigan Athletic",
        "team": "Burton Albion",
        "foot": "Right",
        "birthYear": 1995,
        "age": "23",
        "name": "Devante Cole"
    },
    {
        "id": "GIZTQNRUG4======",
        "sofifaID": "238647",
        "lastUpdate": "Fri Dec 14 13:30:36 2018",
        "picture": "https://cdn.sofifa.org/players/10/19/238647.png",
        "sofifaFollow": "1",
        "position": "RM",
        "wage": "&euro;1K",
        "value": "&euro;750K",
        "potential": "72",
        "rate": "66",
        "jerseyNumber": "17",
        "country": "Germany",
        "team": "FSV Zwickau",
        "foot": "Right",
        "birthYear": 1995,
        "age": "22",
        "name": "Morris Schr\u00f6ter"
    },
    {
        "id": "GIYDEOBRHE======",
        "sofifaID": "202819",
        "lastUpdate": "Fri Dec 14 13:30:36 2018",
        "picture": "https://cdn.sofifa.org/players/10/19/202819.png",
        "sofifaFollow": "29",
        "position": "SUB",
        "wage": "&euro;2K",
        "value": "&euro;750K",
        "potential": "72",
        "rate": "66",
        "jerseyNumber": "7",
        "country": "Republic of Ireland",
        "team": "Aberdeen",
        "foot": "Right",
        "birthYear": 1992,
        "age": "25",
        "name": "Chris Forrester"
    },
    {
        "id": "GIZDIMBWGU======",
        "sofifaID": "224065",
        "lastUpdate": "Fri Dec 14 13:30:36 2018",
        "picture": "https://cdn.sofifa.org/players/10/19/224065.png",
        "sofifaFollow": "3",
        "position": "LCM",
        "wage": "&euro;5K",
        "value": "&euro;975K",
        "potential": "75",
        "rate": "66",
        "jerseyNumber": "8",
        "country": "Argentina",
        "natioalTeam": "Independiente",
        "team": "Defensa y Justicia",
        "foot": "Right",
        "birthYear": 1995,
        "age": "23",
        "name": "Domingo Blanco (Domingo Felipe Blanco) "
    },
    {
        "id": "GIYTIMBYGE======",
        "sofifaID": "214081",
        "lastUpdate": "Fri Dec 14 13:30:36 2018",
        "picture": "https://cdn.sofifa.org/players/10/19/214081.png",
        "sofifaFollow": "5",
        "position": "SUB",
        "wage": "&euro;1K",
        "value": "&euro;725K",
        "potential": "71",
        "rate": "66",
        "jerseyNumber": "4",
        "country": "Colombia",
        "team": "Junior FC",
        "foot": "Right",
        "birthYear": 1993,
        "age": "24",
        "name": "David Murillo (Jes\u00fas David Murillo Le\u00f3n) "
    },
    {
        "id": "GE4DMOJTG4======",
        "sofifaID": "186937",
        "lastUpdate": "Fri Dec 14 13:30:36 2018",
        "picture": "https://cdn.sofifa.org/players/10/19/186937.png",
        "sofifaFollow": "0",
        "position": "SUB",
        "wage": "&euro;3K",
        "value": "&euro;200K",
        "potential": "66",
        "rate": "66",
        "jerseyNumber": "39",
        "country": "Uruguay",
        "team": "Atl&eacute;tico Tucum&aacute;n",
        "foot": "Left",
        "birthYear": 1984,
        "age": "34",
        "name": "Andr\u00e9s Lamas (Andr\u00e9s Lamas Bervejillo) "
    },
    {
        "id": "GIZTKMBXGM======",
        "sofifaID": "235073",
        "lastUpdate": "Fri Dec 14 13:30:36 2018",
        "picture": "https://cdn.sofifa.org/players/10/19/235073.png",
        "sofifaFollow": "32",
        "position": "SUB",
        "wage": "&euro;4K",
        "value": "&euro;1M",
        "potential": "79",
        "rate": "66",
        "jerseyNumber": "36",
        "country": "Switzerland",
        "team": "TSG 1899 Hoffenheim",
        "foot": "Right",
        "birthYear": 1997,
        "age": "20",
        "name": "Gregor Kobel"
    },
    {
        "id": "GIYDEMZQGE======",
        "sofifaID": "202301",
        "lastUpdate": "Fri Dec 14 13:30:36 2018",
        "picture": "https://cdn.sofifa.org/players/10/19/202301.png",
        "sofifaFollow": "0",
        "position": "RM",
        "wage": "&euro;2K",
        "value": "&euro;625K",
        "potential": "66",
        "rate": "66",
        "jerseyNumber": "13",
        "country": "Korea Republic",
        "team": "Jeju United FC",
        "foot": "Right",
        "birthYear": 1989,
        "age": "29",
        "name": " \u91d1\u6052\u5357 (Ho-Nam Kim) "
    },
    {
        "id": "GIYTKMZWGM======",
        "sofifaID": "215363",
        "lastUpdate": "Fri Dec 14 13:30:36 2018",
        "picture": "https://cdn.sofifa.org/players/10/19/215363.png",
        "sofifaFollow": "1",
        "position": "SUB",
        "wage": "&euro;1K",
        "value": "&euro;900K",
        "potential": "78",
        "rate": "66",
        "jerseyNumber": "12",
        "country": "Italy",
        "team": "Benevento",
        "foot": "Right",
        "birthYear": 1996,
        "age": "22",
        "name": "Lorenzo Montip\u00f3"
    },
    {
        "id": "GIYTANZUGI======",
        "sofifaID": "210742",
        "lastUpdate": "Fri Dec 14 13:30:36 2018",
        "picture": "https://cdn.sofifa.org/players/10/19/210742.png",
        "sofifaFollow": "70",
        "position": "RCM",
        "wage": "&euro;3K",
        "value": "&euro;900K",
        "potential": "73",
        "rate": "66",
        "jerseyNumber": "8",
        "country": "Sweden",
        "team": "Vejle Boldklub",
        "foot": "Right",
        "birthYear": 1995,
        "age": "22",
        "name": "Melker Hallberg"
    },
    {
        "id": "GIYDAMRVGY======",
        "sofifaID": "200256",
        "lastUpdate": "Fri Dec 14 13:30:38 2018",
        "picture": "https://cdn.sofifa.org/players/10/19/200256.png",
        "sofifaFollow": "0",
        "position": "LDM",
        "wage": "&euro;1K",
        "value": "&euro;600K",
        "potential": "67",
        "rate": "66",
        "jerseyNumber": "8",
        "country": "Germany",
        "team": "SV Meppen",
        "foot": "Left",
        "birthYear": 1991,
        "age": "27",
        "name": "Thilo Leugers"
    },
    {
        "id": "GIYTKOBWGQ======",
        "sofifaID": "215864",
        "lastUpdate": "Fri Dec 14 13:30:38 2018",
        "picture": "https://cdn.sofifa.org/players/10/19/215864.png",
        "sofifaFollow": "30",
        "position": "LS",
        "wage": "&euro;13K",
        "value": "&euro;1M",
        "potential": "75",
        "rate": "66",
        "jerseyNumber": "11",
        "country": "Ghana",
        "natioalTeam": "Rangers FC",
        "team": "Blackpool",
        "foot": "Right",
        "birthYear": 1995,
        "age": "23",
        "name": "Joe Dodoo"
    },
    {
        "id": "GIYDSMRRGA======",
        "sofifaID": "209210",
        "lastUpdate": "Fri Dec 14 13:30:38 2018",
        "picture": "https://cdn.sofifa.org/players/10/19/209210.png",
        "sofifaFollow": "6",
        "position": "LCB",
        "wage": "&euro;2K",
        "value": "&euro;700K",
        "potential": "70",
        "rate": "66",
        "jerseyNumber": "2",
        "country": "Australia",
        "team": "Perth Glory",
        "foot": "Left",
        "birthYear": 1994,
        "age": "24",
        "name": "Alex Grant (Alexander Grant) "
    },
    {
        "id": "GIYDEMRZGU======",
        "sofifaID": "202295",
        "lastUpdate": "Fri Dec 14 13:30:38 2018",
        "picture": "https://cdn.sofifa.org/players/10/19/202295.png",
        "sofifaFollow": "0",
        "position": "SUB",
        "wage": "&euro;3K",
        "value": "&euro;650K",
        "potential": "66",
        "rate": "66",
        "jerseyNumber": "9",
        "country": "Korea Republic",
        "team": "Suwon Samsung Bluewings",
        "foot": "Left",
        "birthYear": 1988,
        "age": "29",
        "name": " \u6734\u57fa\u680b (Gi-Dong Park) "
    },
    {
        "id": "GE4DMNBSGI======",
        "sofifaID": "186422",
        "lastUpdate": "Fri Dec 14 13:30:38 2018",
        "picture": "https://cdn.sofifa.org/players/10/19/186422.png",
        "sofifaFollow": "13",
        "position": "RM",
        "wage": "&euro;4K",
        "value": "&euro;675K",
        "potential": "66",
        "rate": "66",
        "jerseyNumber": "7",
        "country": "Republic of Ireland",
        "team": "Bradford City",
        "foot": "Right",
        "birthYear": 1990,
        "age": "27",
        "name": "Sean Scannell"
    },
    {
        "id": "GE4TAMBRGU======",
        "sofifaID": "190015",
        "lastUpdate": "Fri Dec 14 13:30:38 2018",
        "picture": "https://cdn.sofifa.org/players/10/19/190015.png",
        "sofifaFollow": "2",
        "position": "LM",
        "wage": "&euro;2K",
        "value": "&euro;575K",
        "potential": "66",
        "rate": "66",
        "jerseyNumber": "8",
        "country": "Senegal",
        "team": "US Orl&eacute;ans Loiret Football",
        "foot": "Left",
        "birthYear": 1987,
        "age": "31",
        "name": "Ousmane Cissokho (Mame Ousmane Cissokho) "
    },
    {
        "id": "GI2DINJUGY======",
        "sofifaID": "244546",
        "lastUpdate": "Fri Dec 14 13:30:38 2018",
        "picture": "https://cdn.sofifa.org/players/10/19/244546.png",
        "sofifaFollow": "0",
        "position": "LCM",
        "wage": "&euro;1K",
        "value": "&euro;925K",
        "potential": "74",
        "rate": "66",
        "jerseyNumber": "21",
        "country": "Italy",
        "team": "Cittadella",
        "foot": "Right",
        "birthYear": 1996,
        "age": "22",
        "name": "Federico Proia"
    },
    {
        "id": "GIZTQMJTG4======",
        "sofifaID": "238137",
        "lastUpdate": "Fri Dec 14 13:30:38 2018",
        "picture": "https://cdn.sofifa.org/players/10/19/238137.png",
        "sofifaFollow": "1",
        "position": "RB",
        "wage": "&euro;3K",
        "value": "&euro;550K",
        "potential": "66",
        "rate": "66",
        "jerseyNumber": "2",
        "country": "Japan",
        "team": "Cerezo Osaka",
        "foot": "Right",
        "birthYear": 1991,
        "age": "26",
        "name": " \u9678"
    },
    {
        "id": "GE3DKMJXGY======",
        "sofifaID": "165176",
        "lastUpdate": "Fri Dec 14 13:30:38 2018",
        "picture": "https://cdn.sofifa.org/players/10/19/165176.png",
        "sofifaFollow": "3",
        "position": "RES",
        "wage": "&euro;4K",
        "value": "&euro;400K",
        "potential": "66",
        "rate": "66",
        "jerseyNumber": "11",
        "country": "Germany",
        "team": "SSV Jahn Regensburg",
        "foot": "Right",
        "birthYear": 1985,
        "age": "33",
        "name": "Sebastian Freis"
    },
    {
        "id": "GE4TEMBWGM======",
        "sofifaID": "192063",
        "lastUpdate": "Fri Dec 14 13:30:38 2018",
        "picture": "https://cdn.sofifa.org/players/10/19/192063.png",
        "sofifaFollow": "0",
        "position": "ST",
        "wage": "&euro;3K",
        "value": "&euro;675K",
        "potential": "66",
        "rate": "66",
        "jerseyNumber": "21",
        "country": "Brazil",
        "team": "Wis\u0142a P\u0142ock",
        "foot": "Right",
        "birthYear": 1989,
        "age": "28",
        "name": "Ricardo Cavalcante Mendes"
    },
    {
        "id": "GIZDQNBQHA======",
        "sofifaID": "228408",
        "lastUpdate": "Fri Dec 14 13:30:41 2018",
        "picture": "https://cdn.sofifa.org/players/10/19/228408.png",
        "sofifaFollow": "51",
        "position": "SUB",
        "wage": "&euro;13K",
        "value": "&euro;1.1M",
        "potential": "78",
        "rate": "66",
        "jerseyNumber": "31",
        "country": "Republic of Ireland",
        "natioalTeam": "Wolverhampton Wanderers",
        "team": "Walsall",
        "foot": "Right",
        "birthYear": 1998,
        "age": "20",
        "name": "Connor Ronan"
    },
    {
        "id": "GE4TQNZSGE======",
        "sofifaID": "198721",
        "lastUpdate": "Fri Dec 14 13:30:41 2018",
        "picture": "https://cdn.sofifa.org/players/10/19/198721.png",
        "sofifaFollow": "0",
        "position": "SUB",
        "wage": "&euro;1K",
        "value": "&euro;625K",
        "potential": "67",
        "rate": "66",
        "jerseyNumber": "23",
        "country": "Italy",
        "team": "Padova",
        "foot": "Right",
        "birthYear": 1991,
        "age": "26",
        "name": "Daniel Cappelletti"
    },
    {
        "id": "GIZTKMZSHA======",
        "sofifaID": "235328",
        "lastUpdate": "Fri Dec 14 13:30:41 2018",
        "picture": "https://cdn.sofifa.org/players/10/19/235328.png",
        "sofifaFollow": "1",
        "position": "LM",
        "wage": "&euro;4K",
        "value": "&euro;875K",
        "potential": "72",
        "rate": "66",
        "jerseyNumber": "33",
        "country": "Italy",
        "team": "Frosinone",
        "foot": "Left",
        "birthYear": 1994,
        "age": "23",
        "name": "Andrea Beghetto"
    },
    {
        "id": "GIZDCNJQGM======",
        "sofifaID": "221503",
        "lastUpdate": "Fri Dec 14 13:30:41 2018",
        "picture": "https://cdn.sofifa.org/players/10/19/221503.png",
        "sofifaFollow": "12",
        "position": "SUB",
        "wage": "&euro;3K",
        "value": "&euro;700K",
        "potential": "66",
        "rate": "66",
        "jerseyNumber": "19",
        "country": "United States",
        "team": "Seattle Sounders FC",
        "foot": "Right",
        "birthYear": 1991,
        "age": "26",
        "name": "Harry Shipp"
    },
    {
        "id": "GIYDKMZXHA======",
        "sofifaID": "205378",
        "lastUpdate": "Fri Dec 14 13:30:41 2018",
        "picture": "https://cdn.sofifa.org/players/10/19/205378.png",
        "sofifaFollow": "3",
        "position": "SUB",
        "wage": "&euro;4K",
        "value": "&euro;525K",
        "potential": "67",
        "rate": "66",
        "jerseyNumber": "1",
        "country": "France",
        "team": "N&icirc;mes Olympique",
        "foot": "Right",
        "birthYear": 1992,
        "age": "25",
        "name": "Baptiste Valette"
    },
    {
        "id": "GE4TCNJVGI======",
        "sofifaID": "191552",
        "lastUpdate": "Fri Dec 14 13:30:41 2018",
        "picture": "https://cdn.sofifa.org/players/10/19/191552.png",
        "sofifaFollow": "1",
        "position": "RCM",
        "wage": "&euro;3K",
        "value": "&euro;375K",
        "potential": "66",
        "rate": "66",
        "jerseyNumber": "39",
        "country": "Japan",
        "team": "Vissel Kobe",
        "foot": "Right",
        "birthYear": 1985,
        "age": "32",
        "name": " \u96c5\u5f66"
    },
    {
        "id": "GIYTCMBQGI======",
        "sofifaID": "211002",
        "lastUpdate": "Fri Dec 14 13:30:41 2018",
        "picture": "https://cdn.sofifa.org/players/10/19/211002.png",
        "sofifaFollow": "0",
        "position": "RCB",
        "wage": "&euro;2K",
        "value": "&euro;500K",
        "potential": "66",
        "rate": "66",
        "jerseyNumber": "3",
        "country": "Korea Republic",
        "team": "Shimizu S-Pulse",
        "foot": "Right",
        "birthYear": 1989,
        "age": "29",
        "name": " \u9ec4\u9521\u6d69 (Seok-Ho Hwang) "
    },
    {
        "id": "GE4TGOBVGE======",
        "sofifaID": "193851",
        "lastUpdate": "Fri Dec 14 13:30:41 2018",
        "picture": "https://cdn.sofifa.org/players/10/19/193851.png",
        "sofifaFollow": "3",
        "position": "LDM",
        "wage": "&euro;2K",
        "value": "&euro;650K",
        "potential": "66",
        "rate": "66",
        "jerseyNumber": "23",
        "country": "Poland",
        "team": "VfL Osnabr&uuml;ck",
        "foot": "Right",
        "birthYear": 1990,
        "age": "27",
        "name": "David Blacha"
    },
    {
        "id": "GIZDKOBUHE======",
        "sofifaID": "225849",
        "lastUpdate": "Fri Dec 14 13:30:41 2018",
        "picture": "https://cdn.sofifa.org/players/10/19/225849.png",
        "sofifaFollow": "3",
        "position": "RES",
        "wage": "&euro;2K",
        "value": "&euro;825K",
        "potential": "69",
        "rate": "66",
        "jerseyNumber": "7",
        "country": "Germany",
        "team": "SV Wehen Wiesbaden",
        "foot": "Left",
        "birthYear": 1995,
        "age": "23",
        "name": "Maximilian Dittgen"
    },
    {
        "id": "GIZTKMZSGQ======",
        "sofifaID": "235324",
        "lastUpdate": "Fri Dec 14 13:30:41 2018",
        "picture": "https://cdn.sofifa.org/players/10/19/235324.png",
        "sofifaFollow": "1",
        "position": "CAM",
        "wage": "&euro;2K",
        "value": "&euro;850K",
        "potential": "71",
        "rate": "66",
        "jerseyNumber": "11",
        "country": "Netherlands",
        "natioalTeam": "Heracles Almelo",
        "team": "FC Emmen",
        "foot": "Right",
        "birthYear": 1995,
        "age": "23",
        "name": "Reuven Niemeijer"
    },
    {
        "id": "GI2DCNBWGI======",
        "sofifaID": "241462",
        "lastUpdate": "Fri Dec 14 13:30:44 2018",
        "picture": "https://cdn.sofifa.org/players/10/19/241462.png",
        "sofifaFollow": "1",
        "position": "SUB",
        "wage": "&euro;6K",
        "value": "&euro;1M",
        "potential": "76",
        "rate": "66",
        "jerseyNumber": "19",
        "country": "Uruguay",
        "natioalTeam": "Villarreal CF",
        "team": "Gimn&agrave;stic de Tarragona",
        "foot": "Right",
        "birthYear": 1997,
        "age": "21",
        "name": "Ramiro Guerra"
    },
    {
        "id": "GE4TKMJSGY======",
        "sofifaID": "195126",
        "lastUpdate": "Fri Dec 14 13:30:44 2018",
        "picture": "https://cdn.sofifa.org/players/10/19/195126.png",
        "sofifaFollow": "8",
        "position": "ST",
        "wage": "&euro;4K",
        "value": "&euro;825K",
        "potential": "69",
        "rate": "66",
        "jerseyNumber": "9",
        "country": "England",
        "team": "Doncaster Rovers",
        "foot": "Right",
        "birthYear": 1992,
        "age": "26",
        "name": "John Marquis"
    },
    {
        "id": "GI2DCNBWGU======",
        "sofifaID": "241465",
        "lastUpdate": "Fri Dec 14 13:30:44 2018",
        "picture": "https://cdn.sofifa.org/players/10/19/241465.png",
        "sofifaFollow": "0",
        "position": "SUB",
        "wage": "&euro;6K",
        "value": "&euro;975K",
        "potential": "75",
        "rate": "66",
        "jerseyNumber": "19",
        "country": "Spain",
        "natioalTeam": "Villarreal CF",
        "team": "Elche CF",
        "foot": "Right",
        "birthYear": 1997,
        "age": "21",
        "name": "V\u00edctor Moya Mart\u00ednez"
    },
    {
        "id": "GE4TSMJVHE======",
        "sofifaID": "199159",
        "lastUpdate": "Fri Dec 14 13:30:44 2018",
        "picture": "https://cdn.sofifa.org/players/10/19/199159.png",
        "sofifaFollow": "13",
        "position": "SUB",
        "wage": "&euro;4K",
        "value": "&euro;625K",
        "potential": "67",
        "rate": "67",
        "jerseyNumber": "26",
        "country": "Australia",
        "team": "Melbourne City FC",
        "foot": "Right",
        "birthYear": 1990,
        "age": "28",
        "name": "Luke Brattan"
    },
    {
        "id": "GIZDAOJRGU======",
        "sofifaID": "220915",
        "lastUpdate": "Fri Dec 14 13:30:44 2018",
        "picture": "https://cdn.sofifa.org/players/10/19/220915.png",
        "sofifaFollow": "9",
        "position": "SUB",
        "wage": "&euro;5K",
        "value": "&euro;1.1M",
        "potential": "75",
        "rate": "67",
        "jerseyNumber": "11",
        "country": "Italy",
        "team": "SPAL",
        "foot": "Right",
        "birthYear": 1996,
        "age": "22",
        "name": "Gabriele Moncini"
    },
    {
        "id": "GIZTEMJZGI======",
        "sofifaID": "232192",
        "lastUpdate": "Fri Dec 14 13:30:44 2018",
        "picture": "https://cdn.sofifa.org/players/10/19/232192.png",
        "sofifaFollow": "21",
        "position": "LDM",
        "wage": "&euro;10K",
        "value": "&euro;1M",
        "potential": "78",
        "rate": "66",
        "jerseyNumber": "35",
        "country": "Luxembourg",
        "natioalTeam": "Olympique Lyonnais",
        "team": "ESTAC Troyes",
        "foot": "Right",
        "birthYear": 1997,
        "age": "21",
        "name": "Christopher Martins Pereira"
    },
    {
        "id": "GIZTENRZHA======",
        "sofifaID": "232698",
        "lastUpdate": "Fri Dec 14 13:30:44 2018",
        "picture": "https://cdn.sofifa.org/players/10/19/232698.png",
        "sofifaFollow": "0",
        "position": "SUB",
        "wage": "&euro;5K",
        "value": "&euro;600K",
        "potential": "67",
        "rate": "67",
        "jerseyNumber": "10",
        "country": "Argentina",
        "team": "Patronato",
        "foot": "Right",
        "birthYear": 1986,
        "age": "32",
        "name": "Mat\u00edas Garrido"
    },
    {
        "id": "GIZTMNJTG4======",
        "sofifaID": "236537",
        "lastUpdate": "Fri Dec 14 13:30:44 2018",
        "picture": "https://cdn.sofifa.org/players/10/19/236537.png",
        "sofifaFollow": "8",
        "position": "SUB",
        "wage": "&euro;3K",
        "value": "&euro;925K",
        "potential": "75",
        "rate": "67",
        "jerseyNumberNational": "17",
        "jerseyNumber": "21",
        "country": "Mexico",
        "natioalTeam": "Santos Laguna",
        "team": "Mexico",
        "foot": "Left",
        "birthYear": 1998,
        "age": "19",
        "name": "Gerardo Arteaga"
    },
    {
        "id": "GEYDINBUGI======",
        "sofifaID": "104442",
        "lastUpdate": "Fri Dec 14 13:30:44 2018",
        "picture": "https://cdn.sofifa.org/players/10/19/104442.png",
        "sofifaFollow": "2",
        "position": "RM",
        "wage": "&euro;3K",
        "value": "&euro;375K",
        "potential": "67",
        "rate": "67",
        "jerseyNumber": "29",
        "country": "Scotland",
        "team": "Kilmarnock",
        "foot": "Right",
        "birthYear": 1983,
        "age": "34",
        "name": "Chris Burke"
    },
    {
        "id": "GIZTGMRQG4======",
        "sofifaID": "233207",
        "lastUpdate": "Fri Dec 14 13:30:44 2018",
        "picture": "https://cdn.sofifa.org/players/10/19/233207.png",
        "sofifaFollow": "1",
        "position": "RB",
        "wage": "&euro;3K",
        "value": "&euro;825K",
        "potential": "71",
        "rate": "67",
        "jerseyNumber": "2",
        "country": "Japan",
        "team": "FC Tokyo",
        "foot": "Right",
        "birthYear": 1994,
        "age": "24",
        "name": " \u6210"
    },
    {
        "id": "GIYTINZXHE======",
        "sofifaID": "214779",
        "lastUpdate": "Fri Dec 14 13:30:46 2018",
        "picture": "https://cdn.sofifa.org/players/10/19/214779.png",
        "sofifaFollow": "0",
        "position": "RES",
        "wage": "&euro;7K",
        "value": "&euro;1M",
        "potential": "72",
        "rate": "67",
        "jerseyNumber": "32",
        "country": "Argentina",
        "team": "Club Atl&eacute;tico Lan&uacute;s",
        "foot": "Right",
        "birthYear": 1993,
        "age": "25",
        "name": "Bruno Vides (Bruno Leonel Vides) "
    },
    {
        "id": "GIZDSNRRHE======",
        "sofifaID": "229619",
        "lastUpdate": "Fri Dec 14 13:30:46 2018",
        "picture": "https://cdn.sofifa.org/players/10/19/229619.png",
        "sofifaFollow": "13",
        "position": "LCB",
        "wage": "&euro;2K",
        "value": "&euro;900K",
        "potential": "73",
        "rate": "67",
        "jerseyNumber": "5",
        "country": "Uruguay",
        "team": "V&aring;lerenga Fotball",
        "foot": "Left",
        "birthYear": 1993,
        "age": "24",
        "name": "Felipe Carvalho (Luis Felipe Carvalho da Silva) "
    },
    {
        "id": "GI2DKNBZGI======",
        "sofifaID": "245492",
        "lastUpdate": "Fri Dec 14 13:30:46 2018",
        "picture": "https://cdn.sofifa.org/players/10/19/245492.png",
        "sofifaFollow": "1",
        "position": "SUB",
        "wage": "&euro;3K",
        "value": "&euro;1.3M",
        "potential": "78",
        "rate": "67",
        "jerseyNumber": "31",
        "country": "Morocco",
        "team": "M&aacute;laga CF",
        "foot": "Right",
        "birthYear": 1998,
        "age": "20",
        "name": "Hicham Boussefiane"
    },
    {
        "id": "GIZDCNRZGY======",
        "sofifaID": "221696",
        "lastUpdate": "Fri Dec 14 13:30:46 2018",
        "picture": "https://cdn.sofifa.org/players/10/19/221696.png",
        "sofifaFollow": "4",
        "position": "RCM",
        "wage": "&euro;3K",
        "value": "&euro;675K",
        "potential": "66",
        "rate": "66",
        "jerseyNumber": "15",
        "country": "United States",
        "team": "New York City FC",
        "foot": "Right",
        "birthYear": 1991,
        "age": "27",
        "name": "Thomas McNamara"
    },
    {
        "id": "GE3TOOJRGI======",
        "sofifaID": "177912",
        "lastUpdate": "Fri Dec 14 13:30:46 2018",
        "picture": "https://cdn.sofifa.org/players/10/19/177912.png",
        "sofifaFollow": "0",
        "position": "SUB",
        "wage": "&euro;2K",
        "value": "&euro;700K",
        "potential": "67",
        "rate": "67",
        "jerseyNumber": "8",
        "country": "Norway",
        "team": "V&aring;lerenga Fotball",
        "foot": "Right",
        "birthYear": 1988,
        "age": "30",
        "name": "Magnus Lekven"
    },
    {
        "id": "GIZTMMBSGQ======",
        "sofifaID": "236024",
        "lastUpdate": "Fri Dec 14 13:30:46 2018",
        "picture": "https://cdn.sofifa.org/players/10/19/236024.png",
        "sofifaFollow": "1",
        "position": "LM",
        "wage": "&euro;3K",
        "value": "&euro;950K",
        "potential": "70",
        "rate": "67",
        "jerseyNumber": "19",
        "country": "France",
        "team": "Stade Brestois 29",
        "foot": "Right",
        "birthYear": 1993,
        "age": "25",
        "name": "Ferris N'Goma"
    },
    {
        "id": "GIYDEMRTGE======",
        "sofifaID": "202231",
        "lastUpdate": "Fri Dec 14 13:30:46 2018",
        "picture": "https://cdn.sofifa.org/players/10/19/202231.png",
        "sofifaFollow": "1",
        "position": "SUB",
        "wage": "&euro;3K",
        "value": "&euro;575K",
        "potential": "67",
        "rate": "67",
        "jerseyNumber": "16",
        "country": "United States",
        "team": "Columbus Crew SC",
        "foot": "Right",
        "birthYear": 1988,
        "age": "29",
        "name": "Hector Jimenez (H\u00e9ctor Jim\u00e9nez) "
    },
    {
        "id": "GIZTINZUGE======",
        "sofifaID": "234741",
        "lastUpdate": "Fri Dec 14 13:30:46 2018",
        "picture": "https://cdn.sofifa.org/players/10/19/234741.png",
        "sofifaFollow": "5",
        "position": "RCM",
        "wage": "&euro;3K",
        "value": "&euro;1.2M",
        "potential": "76",
        "rate": "67",
        "jerseyNumber": "6",
        "country": "Netherlands",
        "team": "PEC Zwolle",
        "foot": "Right",
        "birthYear": 1997,
        "age": "21",
        "name": "Gustavo Hamer"
    },
    {
        "id": "GIYDSNBQGI======",
        "sofifaID": "209402",
        "lastUpdate": "Fri Dec 14 13:30:46 2018",
        "picture": "https://cdn.sofifa.org/players/10/19/209402.png",
        "sofifaFollow": "6",
        "position": "SUB",
        "wage": "&euro;4K",
        "value": "&euro;1M",
        "potential": "72",
        "rate": "67",
        "jerseyNumber": "29",
        "country": "Netherlands",
        "team": "Sint-Truidense VV",
        "foot": "Right",
        "birthYear": 1995,
        "age": "22",
        "name": "Elton Acolatse"
    },
    {
        "id": "GIYTMOBSGM======",
        "sofifaID": "216823",
        "lastUpdate": "Fri Dec 14 13:30:46 2018",
        "picture": "https://cdn.sofifa.org/players/10/19/216823.png",
        "sofifaFollow": "39",
        "position": "SUB",
        "wage": "&euro;3K",
        "value": "&euro;1M",
        "potential": "71",
        "rate": "67",
        "jerseyNumber": "19",
        "country": "Netherlands",
        "team": "Heracles Almelo",
        "foot": "Right",
        "birthYear": 1994,
        "age": "23",
        "name": "Vincent Vermeij"
    },
    {
        "id": "GIZDINJQHE======",
        "sofifaID": "224509",
        "lastUpdate": "Fri Dec 14 13:30:48 2018",
        "picture": "https://cdn.sofifa.org/players/10/19/224509.png",
        "sofifaFollow": "23",
        "position": "SUB",
        "wage": "&euro;6K",
        "value": "&euro;1M",
        "potential": "73",
        "rate": "67",
        "jerseyNumber": "16",
        "country": "Mexico",
        "team": "Santos Laguna",
        "foot": "Right",
        "birthYear": 1996,
        "age": "22",
        "name": "Ulises Rivas (Ulises Rivas Gilio) "
    },
    {
        "id": "GIZDCNRYGQ======",
        "sofifaID": "221684",
        "lastUpdate": "Fri Dec 14 13:30:48 2018",
        "picture": "https://cdn.sofifa.org/players/10/19/221684.png",
        "sofifaFollow": "1",
        "position": "LB",
        "wage": "&euro;3K",
        "value": "&euro;725K",
        "potential": "68",
        "rate": "67",
        "jerseyNumber": "2",
        "country": "United States",
        "team": "New York City FC",
        "foot": "Left",
        "birthYear": 1991,
        "age": "26",
        "name": "Ben Sweat"
    }
]